Workbook

Sheet 📋 Tracker
A1: 🚀 NEGOCIOS CUANTICOS · Sistema de Automatización · Proyecto Piloto → Escala
A2: Sem | B2: Fecha | C2: Tarea | D2: Módulo | E2: Fase | F2: Descripción | G2: Resp. | H2: Estado | I2: Prioridad | J2: Negocio | K2: Herramienta | L2: KPI / Output | M2: Notas
A3: 1 | B3: 46102 | C3: Reunión con cliente — definir piloto | D3: Estrategia | E3: Planeación | F3: Reunión sábado: elegir negocio piloto, acordar modelo económico (setup+mensualidad+comisión), revisar flujos del Drive | G3: Valentina | H3: Done | I3: High | J3: Negocios Cuanticos | K3: Presencial | L3: Acta con decisiones firmadas | M3: Salir con negocio piloto definido
A4: 1 | B4: 46102 | C4: Documentar acuerdos económicos | D4: Estrategia | E4: Planeación | F4: Formalizar: setup fee, mensualidad por negocio, % comisión por tipo de venta | G4: Valentina | H4: Done | I4: High | J4: Negocios Cuanticos | K4: Google Docs | L4: Acuerdo firmado o por escrito
A5: 1 | B5: 46104 | C5: Revisar Drive del cliente | D5: Organización | E5: Análisis | F5: Auditar carpetas compartidas. Identificar catálogos, listas clientes, registros de pedidos, contratos proveedores | G5: Daniel | H5: In Progress | I5: High | J5: Negocios Cuanticos | K5: Google Drive | L5: Mapa de información disponible | M5: Hay mucho desorden — priorizar lo crítico
A6: 1 | B6: 46104 | C6: Mapear flujo AS-IS negocio piloto | D6: Ventas | E6: Análisis | F6: Cómo llega hoy una cotización, cuánto tarda, cómo se cierra, cómo se calcula la comisión | G6: Valentina | H6: In Progress | I6: High | J6: Piloto | K6: Manual | L6: Diagrama flujo actual documentado | M6: Base para diseñar la automatización
A7: 1 | B7: 46105 | C7: Ver video n8n principiantes (Automaize) | D7: Aprendizaje | E7: Formación | F7: Canal Automaize: N8N para Principiantes desde CERO. Entender nodos, webhooks y conexiones básicas | G7: Valentina | H7: In Progress | I7: High | J7: Todos | K7: YouTube | L7: Entender nodos, webhooks y flujos | M7: Obligatorio antes de tocar n8n
A8: 1 | B8: 46106 | C8: Crear repositorio automation-docs | D8: Infra | E8: Setup | F8: GitHub repo público o privado + README inicial + estructura de carpetas base | G8: Valentina | H8: Pending | I8: Medium | J8: Todos | K8: GitHub | L8: Repo creado y compartido con Daniel | M8: Plan gratuito de GitHub es suficiente
A9: 1 | B9: 46106 | C9: Comprar suscripciones (cliente paga) | D9: Infra | E9: Setup | F9: Confirmar que el cliente compra: Hostinger VPS, n8n Cloud o self-hosted, WATI/Pancake, Claude API | G9: Valentina | H9: Pending | I9: High | J9: Todos | K9: Varios | L9: Acceso a todas las herramientas | M9: Sin esto no se puede arrancar técnicamente
A10: 2 | B10: 46109 | C10: Instalar n8n en Hostinger | D10: Infra | E10: Setup | F10: VPS KVM2 Brasil + Docker + n8n self-hosted. Configurar dominio y HTTPS | G10: Daniel | H10: Pending | I10: High | J10: Todos | K10: Hostinger / n8n | L10: n8n corriendo en producción | M10: Servidor Brasil = baja latencia Colombia
A11: 2 | B11: 46110 | C11: Conectar Pancake a canales del piloto | D11: Captación | E11: Setup | F11: Vincular Instagram y Facebook del negocio piloto a Pancake. Configurar acceso API | G11: Daniel | H11: Pending | I11: High | J11: Piloto | K11: Pancake | L11: Mensajes llegando a Pancake
A12: 2 | B12: 46111 | C12: Primer webhook: Pancake → n8n | D12: Captación | E12: Automatización | F12: Configurar que cuando llegue un DM, Pancake dispara webhook a n8n. Verificar que llega el JSON | G12: Daniel | H12: Pending | I12: High | J12: Piloto | K12: Pancake + n8n | L12: Primer dato JSON visible en n8n | M12: Este es el 'clic' que lo cambia todo
A13: 2 | B13: 46112 | C13: Obtener API Key de Claude | D13: IA | E13: Setup | F13: Crear cuenta en console.anthropic.com, obtener API key con créditos iniciales | G13: Valentina | H13: Pending | I13: High | J13: Todos | K13: Claude API | L13: API key activa y probada
A14: 2 | B14: 46113 | C14: Primer flujo completo: mensaje → respuesta | D14: Captación | E14: Automatización | F14: DM llega → n8n recibe → Claude genera respuesta → respuesta enviada al cliente. Prueba end-to-end | G14: Daniel | H14: Pending | I14: High | J14: Piloto | K14: n8n + Claude | L14: Respuesta automática en <30 segundos | M14: El primer flujo que funciona es el hito más importante
A15: 3 | B15: 46118 | C15: Subir catálogo de productos a Sheets | D15: Ventas | E15: Setup | F15: Organizar catálogo del negocio piloto en Google Sheets: nombre, precio, descripción, disponibilidad | G15: Valentina | H15: Pending | I15: High | J15: Piloto | K15: Google Sheets | L15: Catálogo limpio y estructurado | M15: La IA necesita esta fuente de verdad
A16: 3 | B16: 46119 | C16: Flujo de cotización automática | D16: Ventas | E16: Automatización | F16: Cliente pide cotización → IA consulta catálogo → genera cotización → envía por WA. Sin intervención humana | G16: Daniel | H16: Pending | I16: High | J16: Piloto | K16: n8n + Claude | L16: Cotización enviada en <1 minuto | M16: Hoy tardan varios minutos o días
A17: 3 | B17: 46120 | C17: Flujo de seguimiento post-cotización | D17: Ventas | E17: Automatización | F17: Si cliente no responde en 24h → mensaje de seguimiento automático. Máximo 2 intentos | G17: Daniel | H17: Pending | I17: Medium | J17: Piloto | K17: n8n + WATI | L17: Tasa seguimiento automatizado | M17: Hoy se hace a mano o no se hace
A18: 3 | B18: 46121 | C18: Captura de leads en Google Sheets | D18: Captación | E18: Automatización | F18: Cada nuevo contacto → n8n registra: fecha, nombre, canal, mensaje, estado en Sheets | G18: Daniel | H18: Pending | I18: High | J18: Piloto | K18: n8n + Sheets | L18: CRM básico funcionando solo | M18: Primer CRM real del negocio
A19: 3 | B19: 46122 | C19: Prueba real con 5 clientes del cliente | D19: Testing | E19: QA | F19: Hacer 5 cotizaciones reales usando el sistema. Medir tiempo, precisión y feedback del cliente final | G19: Valentina | H19: Pending | I19: High | J19: Piloto | K19: Sistema completo | L19: Tiempo cotización, tasa respuesta
A20: 4 | B20: 46125 | C20: Flujo de cierre de venta | D20: Pedidos | E20: Automatización | F20: Cliente acepta cotización → sistema registra pedido automáticamente en Sheets con todos los datos | G20: Daniel | H20: Pending | I20: High | J20: Piloto | K20: n8n + Sheets | L20: Pedidos registrados sin intervención
A21: 4 | B21: 46126 | C21: Cálculo automático de comisión | D21: Pedidos | E21: Automatización | F21: Por cada pedido cerrado → n8n calcula comisión según el % acordado → registra en tabla de comisiones | G21: Daniel | H21: Pending | I21: High | J21: Piloto | K21: n8n + Sheets | L21: Comisión calculada automáticamente | M21: Hoy se hace a mano para 30+ pedidos
A22: 4 | B22: 46127 | C22: Notificación de pedido al cliente | D22: Pedidos | E22: Automatización | F22: Confirmación automática por WA: número pedido, detalle, próximos pasos | G22: Daniel | H22: Pending | I22: Medium | J22: Piloto | K22: n8n + WATI | L22: Confirmación enviada en <1 minuto
A23: 4 | B23: 46128 | C23: Dashboard KPIs semana 1–3 | D23: Analytics | E23: Análisis | F23: Vista consolidada en Sheets: ventas, cotizaciones, conversión, comisiones acumuladas. Fórmulas dinámicas | G23: Valentina | H23: Pending | I23: High | J23: Piloto | K23: Google Sheets | L23: Dashboard actualizado en tiempo real | M23: Base del reporte mensual al cliente
A24: 4 | B24: 46129 | C24: Revisión con cliente — checkpoint Fase 1 | D24: Estrategia | E24: Revisión | F24: Presentar resultados primeras 4 semanas. Ajustar lo que no funciona. Confirmar expansión a siguiente negocio | G24: Valentina | H24: Pending | I24: High | J24: Negocios Cuanticos | K24: Reunión | L24: Cliente aprueba Fase 1 y confirma Fase 2
A25: 5 | B25: 46132 | C25: Definir perfil cliente ideal (ICP) | D25: Prospectación | E25: Análisis | F25: ¿A quién queremos llegar? Sector, tamaño empresa, ciudad, cargo del decisor. Base para el scraping | G25: Valentina | H25: Pending | I25: High | J25: Piloto | K25: Manual | L25: ICP documentado | M25: Sin esto el scraping no sirve
A26: 5 | B26: 46133 | C26: Construir robot de web scraping | D26: Prospectación | E26: Automatización | F26: n8n + herramienta scraping busca empresas por sector en directorios públicos. Extrae nombre, teléfono, email | G26: Daniel | H26: Pending | I26: High | J26: Piloto | K26: n8n + Scraping | L26: Base de datos prospectos estructurada | M26: Cámara Comercio, Páginas Amarillas, LinkedIn
A27: 5 | B27: 46134 | C27: Flujo de contacto inteligente (no spam) | D27: Prospectación | E27: Automatización | F27: Claude personaliza mensaje por empresa. n8n envía por WA/email en horarios óptimos. Máx 1 mensaje inicial | G27: Daniel | H27: Pending | I27: High | J27: Piloto | K27: n8n + Claude | L27: Tasa apertura y respuesta prospectos | M27: Que no parezca spam — personalización es clave
A28: 6 | B28: 46139 | C28: Flujo nutrición de prospectos | D28: Prospectación | E28: Automatización | F28: Prospecto no responde → secuencia de 3 toques en 2 semanas. Cada mensaje diferente, progresivamente más directo | G28: Daniel | H28: Pending | I28: Medium | J28: Piloto | K28: n8n + WATI | L28: Tasa conversión prospecto → cliente
A29: 6 | B29: 46141 | C29: Prueba prospectación con 20 empresas | D29: Prospectación | E29: QA | F29: Lanzar flujo real con 20 empresas del perfil ideal. Medir respuestas, interesados y reuniones agendadas | G29: Valentina | H29: Pending | I29: High | J29: Piloto | K29: Sistema completo | L29: Reuniones agendadas / respuestas
A30: 7 | B30: 46146 | C30: Elegir segundo negocio de Cuanticos | D30: Estrategia | E30: Planeación | F30: Con los resultados del piloto, definir cuál negocio de Cuanticos se automatiza a continuación | G30: Valentina | H30: Pending | I30: High | J30: Negocios Cuanticos | K30: Reunión | L30: Segundo negocio confirmado | M30: El motor ya está construido — esto es config
A31: 7 | B31: 46147 | C31: Replicar motor al segundo negocio | D31: Infra | E31: Automatización | F31: Duplicar workflows en n8n, cambiar configuración: catálogo, número WA, % comisión, plantillas de mensajes | G31: Daniel | H31: Pending | I31: High | J31: Negocio 2 | K31: n8n | L31: Segundo negocio corriendo en <3 días | M31: Esta es la prueba del modelo SaaS
A32: 7 | B32: 46148 | C32: Ajustar dashboard para múltiples negocios | D32: Analytics | E32: Automatización | F32: Consolidar KPIs de negocio 1 y 2 en una vista. Separar comisiones por negocio | G32: Daniel | H32: Pending | I32: Medium | J32: Negocios Cuanticos | K32: Google Sheets | L32: Dashboard multi-negocio funcionando
A33: 8 | B33: 46153 | C33: Revisión general — Fase 2 checkpoint | D33: Estrategia | E33: Revisión | F33: Presentar resultados de ambos negocios. Confirmar tercer negocio. Revisar modelo de comisiones con datos reales | G33: Valentina | H33: Pending | I33: High | J33: Negocios Cuanticos | K33: Reunión | L33: Cliente confirma expansión al resto
A34: 9 | B34: 46160 | C34: Flujo comparación precios Alibaba vs COL | D34: Abastecimiento | E34: Automatización | F34: Sistema busca producto en Alibaba, compara vs precio Colombia, calcula margen y recomienda si importar | G34: Daniel | H34: Pending | I34: Medium | J34: Smart Shoes / Logística | K34: n8n + Scraping | L34: Ahorro identificado por producto | M34: Repuestos y calzado son los casos más claros
A35: 9 | B35: 46161 | C35: Base de datos proveedores validados | D35: Abastecimiento | E35: Setup | F35: Registro estructurado de proveedores Alibaba: producto, precio, tiempos entrega, calificación, historial | G35: Valentina | H35: Pending | I35: Medium | J35: Negocios Cuanticos | K35: Google Sheets | L35: Catálogo proveedores actualizado
A36: 10 | B36: 46167 | C36: Automatizar orden de importación | D36: Abastecimiento | E36: Automatización | F36: Proveedor aprobado → sistema genera orden, actualiza catálogo de productos disponibles, notifica al equipo | G36: Daniel | H36: Pending | I36: Low | J36: Negocios Cuanticos | K36: n8n + Sheets | L36: Tiempo proceso importación reducido | M36: Fase futura — validar primero con flujos manuales
A37: 11 | B37: 46174 | C37: Prueba end-to-end todos los flujos | D37: Testing | E37: QA | F37: Simular ciclo completo por negocio: prospecto → cotización → venta → comisión → dashboard. 0 errores | G37: Daniel | H37: Pending | I37: High | J37: Todos | K37: Sistema completo | L37: 0 errores en flujo completo
A38: 11 | B38: 46175 | C38: Documentar todos los workflows en GitHub | D38: Organización | E38: Documentación | F38: Exportar cada workflow de n8n como JSON. Subir a automation-core con README por flujo | G38: Valentina | H38: Pending | I38: High | J38: Todos | K38: GitHub | L38: Repo actualizado y documentado | M38: Esto es el activo reutilizable del SaaS
A39: 12 | B39: 46181 | C39: Entrega final al cliente | D39: Estrategia | E39: Entrega | F39: Presentación de resultados completos: KPIs, comisiones generadas, flujos activos, plan de crecimiento | G39: Valentina | H39: Pending | I39: High | J39: Negocios Cuanticos | K39: Reunión | L39: Cliente aprueba entrega y renueva
A40: 12 | B40: 46182 | C40: Definir hoja de ruta siguiente trimestre | D40: Estrategia | E40: Planeación | F40: Con datos reales del primer trimestre: qué automatizar a continuación, nuevas líneas (envases, marketplace) | G40: Valentina | H40: Pending | I40: Medium | J40: Negocios Cuanticos | K40: Reunión | L40: Plan Q3 acordado

Sheet 🗺️ Roadmap
B1: 🗺️ ROADMAP · Negocios Cuanticos · Mar – Jun 2026 · 10 Fases
B2: Fase | C2: Período | D2: Semanas | E2: Foco principal | F2: Entregable clave | G2: Negocios | H2: Herramientas | I2: Estado
B3: Fase 1 | C3: Mar 21–27 | D3: Sem 1 | E3: Reunión, acuerdos y análisis | F3: Negocio piloto definido + modelo económico acordado | G3: Negocios Cuanticos | H3: Google Drive, Docs | I3: En Progreso
B4: Fase 2 | C4: Mar 28–Abr 4 | D4: Sem 2 | E4: Setup técnico completo | F4: n8n corriendo + Pancake conectado + primer webhook activo | G4: Todos | H4: Hostinger, n8n, Pancake | I4: Pendiente
B5: Fase 3 | C5: Abr 6–11 | D5: Sem 3 | E5: Cotización automática | F5: Cliente recibe cotización sin que nadie la escriba | G5: Piloto | H5: n8n, Claude, Sheets | I5: Pendiente
B6: Fase 4 | C6: Abr 13–18 | D6: Sem 4 | E6: Pedidos, comisiones y dashboard | F6: Comisión calculada sola + dashboard KPIs en vivo | G6: Piloto | H6: n8n, Sheets | I6: Pendiente
B7: Fase 5 | C7: Abr 20–May 1 | D7: Sem 5–6 | E7: Prospectación inteligente | F7: Robot encuentra y contacta 20+ prospectos/semana | G7: Piloto | H7: n8n, Claude, Scraping | I7: Pendiente
B8: Fase 6 | C8: May 4–15 | D8: Sem 7–8 | E8: Expansión a segundo negocio | F8: Motor replicado en <3 días al segundo negocio de Cuanticos | G8: Negocio 2 | H8: n8n (config) | I8: Pendiente
B9: Fase 7 | C9: May 18–29 | D9: Sem 9–10 | E9: Gestión de proveedores Alibaba | F9: Sistema compara precios Alibaba vs Colombia automáticamente | G9: Smart Shoes/Logística | H9: n8n, Scraping | I9: Pendiente
B10: Fase 8 | C10: Jun 1–5 | D10: Sem 11 | E10: QA y documentación completa | F10: 0 errores en todos los flujos + repo GitHub actualizado | G10: Todos | H10: GitHub, n8n | I10: Pendiente
B11: Fase 9 | C11: Jun 8–12 | D11: Sem 12 | E11: Entrega y cierre Trimestre 1 | F11: Presentación resultados + plan Q3 acordado | G11: Negocios Cuanticos | H11: Reunión | I11: Pendiente
B12: Fase 10 | C12: Jun–Ago | D12: Q3 | E12: Escala: marketplace + envases + más | F12: Nuevas líneas automáticas según resultados Q1 | G12: Nuevos negocios | H12: Stack completo | I12: Futuro

Sheet 📊 KPIs
B1: 📊 DASHBOARD KPIs · Negocios Cuanticos · Actualización automática desde Tracker
B3: AVANCE GENERAL DEL PROYECTO
B4: Métrica | C4: Valor actual | D4: Meta | E4: % avance | F4: Semana | G4: Observación
B5: Tareas completadas | C5: =COUNTIF('📋 Tracker'!H3:H120,"Done") | D5: 35 | F5: 1
B6: Tareas en progreso | C6: =COUNTIF('📋 Tracker'!H3:H120,"In Progress") | F6: 1
B7: Tareas bloqueadas | C7: =COUNTIF('📋 Tracker'!H3:H120,"Blocked") | D7: 0 | F7: 1 | G7: Cualquier bloqueo es urgente
B8: % completado del proyecto | C8: =IFERROR(COUNTIF('📋 Tracker'!H3:H120,"Done")/COUNTIF('📋 Tracker'!H3:H120,"<>"),0) | D8: 1 | F8: 1
B9: High priority pendientes | C9: =COUNTIFS('📋 Tracker'!I3:I120,"High",'📋 Tracker'!H3:H120,"Pending") | D9: 0 | F9: 1 | G9: Estas son las urgentes
B11: PROGRESO POR MÓDULO
B12: Módulo | C12: Done | D12: Total | E12: % Done | F12: — | G12: Comentario
B13: Captación | C13: =COUNTIFS('📋 Tracker'!D3:D120,"Captación",'📋 Tracker'!H3:H120,"Done") | D13: =COUNTIFS('📋 Tracker'!D3:D120,"Captación",'📋 Tracker'!H3:H120,"<>") | E13: =IFERROR(C13/D13,0)
B14: Ventas | C14: =COUNTIFS('📋 Tracker'!D3:D120,"Ventas",'📋 Tracker'!H3:H120,"Done") | D14: =COUNTIFS('📋 Tracker'!D3:D120,"Ventas",'📋 Tracker'!H3:H120,"<>") | E14: =IFERROR(C14/D14,0)
B15: IA | C15: =COUNTIFS('📋 Tracker'!D3:D120,"IA",'📋 Tracker'!H3:H120,"Done") | D15: =COUNTIFS('📋 Tracker'!D3:D120,"IA",'📋 Tracker'!H3:H120,"<>") | E15: =IFERROR(C15/D15,0)
B16: Pedidos | C16: =COUNTIFS('📋 Tracker'!D3:D120,"Pedidos",'📋 Tracker'!H3:H120,"Done") | D16: =COUNTIFS('📋 Tracker'!D3:D120,"Pedidos",'📋 Tracker'!H3:H120,"<>") | E16: =IFERROR(C16/D16,0)
B17: Abastecimiento | C17: =COUNTIFS('📋 Tracker'!D3:D120,"Abastecimiento",'📋 Tracker'!H3:H120,"Done") | D17: =COUNTIFS('📋 Tracker'!D3:D120,"Abastecimiento",'📋 Tracker'!H3:H120,"<>") | E17: =IFERROR(C17/D17,0)
B18: Prospectación | C18: =COUNTIFS('📋 Tracker'!D3:D120,"Prospectación",'📋 Tracker'!H3:H120,"Done") | D18: =COUNTIFS('📋 Tracker'!D3:D120,"Prospectación",'📋 Tracker'!H3:H120,"<>") | E18: =IFERROR(C18/D18,0)
B19: Analytics | C19: =COUNTIFS('📋 Tracker'!D3:D120,"Analytics",'📋 Tracker'!H3:H120,"Done") | D19: =COUNTIFS('📋 Tracker'!D3:D120,"Analytics",'📋 Tracker'!H3:H120,"<>") | E19: =IFERROR(C19/D19,0)
B20: Infra | C20: =COUNTIFS('📋 Tracker'!D3:D120,"Infra",'📋 Tracker'!H3:H120,"Done") | D20: =COUNTIFS('📋 Tracker'!D3:D120,"Infra",'📋 Tracker'!H3:H120,"<>") | E20: =IFERROR(C20/D20,0)
B21: Estrategia | C21: =COUNTIFS('📋 Tracker'!D3:D120,"Estrategia",'📋 Tracker'!H3:H120,"Done") | D21: =COUNTIFS('📋 Tracker'!D3:D120,"Estrategia",'📋 Tracker'!H3:H120,"<>") | E21: =IFERROR(C21/D21,0)
B22: Testing | C22: =COUNTIFS('📋 Tracker'!D3:D120,"Testing",'📋 Tracker'!H3:H120,"Done") | D22: =COUNTIFS('📋 Tracker'!D3:D120,"Testing",'📋 Tracker'!H3:H120,"<>") | E22: =IFERROR(C22/D22,0)
B25: PROYECCIÓN ECONÓMICA
B26: Concepto | C26: Negocio piloto | D26: ×2 negocios | E26: ×3 negocios | F26: ×5 negocios | G26: Nota
B27: Setup fee (una vez) | C27: $2.000 | D27: $2.800 | E27: $3.400 | F27: $5.000 | G27: Desc. en negocios adicionales
B28: Mensualidad / mes | C28: $400 | D28: $800 | E28: $1.200 | F28: $2.000 | G28: $400 por negocio activo
B29: Comisión estimada / mes | C29: $300 | D29: $700 | E29: $1.100 | F29: $2.000 | G29: 2-5% ventas generadas
B30: Ingreso mensual total | C30: $700 | D30: $1.500 | E30: $2.300 | F30: $4.000 | G30: Mensualidad + comisión
B31: Ingreso año 1 (12 meses) | C31: $10.400 | D31: $20.800 | E31: $29.600 | F31: $53.000 | G31: Setup + 12 mensualidades

Sheet 🛠️ Stack
B1: 🛠️ STACK TECNOLÓGICO · Negocios Cuanticos
B2: Herramienta | C2: Propósito | D2: Costo/mes | E2: ¿Quién paga? | F2: Fase | G2: Estado | H2: Notas
B3: ── INFRAESTRUCTURA ──
B4: Hostinger VPS KVM2 | C4: Servidor donde vive n8n | D4: $6.99 | E4: Cuanticos | F4: 1 | G4: ✅ Comprar ya | H4: Servidor Brasil — baja latencia COL
B5: ── ORQUESTACIÓN ──
B6: n8n (self-hosted) | C6: Motor central de automatización | D6: $0 | E6: Cuanticos | F6: 1 | G6: ✅ Comprar ya | H6: Instalar en Hostinger con Docker
B7: ── IA ──
B8: Claude API | C8: Cotizaciones, calificación, respuestas | D8: ~$20-50 | E8: Cuanticos | F8: 2 | G8: ⚙️ Setup sem 2 | H8: HTTP Request en n8n → api.anthropic.com
B9: ── COMUNICACIÓN ──
B10: Pancake.lat | C10: Centraliza IG + FB + WA | D10: $30+ | E10: Cuanticos | F10: 1 | G10: ✅ Comprar ya | H10: Conectar canales del negocio piloto
B11: WATI (WhatsApp BSP) | C11: WA Business API oficial Meta | D11: $49+ | E11: Cuanticos | F11: 2 | G11: ⚙️ Setup sem 2 | H11: Compatible iOS y Android — reemplaza chatbot actual
B12: ── DATOS ──
B13: Google Sheets | C13: CRM, pedidos, comisiones, KPIs | D13: $0 | E13: Cuanticos | F13: 1 | G13: ✅ Activo | H13: Fuente de verdad del negocio
B14: GitHub | C14: Control de versiones y documentación | D14: $0 | E14: Cuanticos | F14: 1 | G14: ✅ Crear ya | H14: Plan gratuito es suficiente
B15: ── PRÓXIMAS FASES ──
B16: Scraping tool | C16: Prospectación de empresas potenciales | D16: $0-20 | E16: Cuanticos | F16: 5 | G16: 🔒 Fase 5 | H16: Directorio Cámara Comercio, LinkedIn
B17: Retell AI | C17: Agentes de voz IA para llamadas B2B | D17: $0.07/min | E17: Cuanticos | F17: 9 | G17: 🔒 Futuro | H17: All-inclusive (LLM+voz+telefonía)
B18: Instantly.ai | C18: Email frío para prospectación masiva | D18: $37 | E18: Cuanticos | F18: 5 | G18: 🔒 Fase 5 | H18: Calentamiento de dominio automático
